feature_splitter/__init__.py
feature_splitter/splitter.py
feature_splitter-0.1.0.dist-info/METADATA
feature_splitter-0.1.0.dist-info/WHEEL
feature_splitter-0.1.0.dist-info/top_level.txt
feature_splitter-0.1.0.dist-info/RECORD
