Metadata-Version: 2.4
Name: feature_splitter
Version: 0.1.0
Summary: Split a DataFrame by column variation and save CSV parts
Author: Your Name
Author-email: your.email@example.com
Requires-Python: >=3.6
Requires-Dist: pandas
Dynamic: author
Dynamic: author-email
Dynamic: requires-dist
Dynamic: requires-python
Dynamic: summary
